socketio_driver/__init__.py
socketio_driver/communicator.py
socketio_driver/config/socketio.py
socketio_driver/drivers/__init__.py
socketio_driver/drivers/socket_driver.py
socketio_driver/facades/__init__.py
socketio_driver/facades/communicator.py
socketio_driver/models/socket_client.py
socketio_driver/providers/__init__.py
socketio_driver/providers/socket_provider.py
masonite_socketio_driver-2.1.0.dist-info/LICENSE
masonite_socketio_driver-2.1.0.dist-info/METADATA
masonite_socketio_driver-2.1.0.dist-info/WHEEL
masonite_socketio_driver-2.1.0.dist-info/top_level.txt
masonite_socketio_driver-2.1.0.dist-info/RECORD
