Metadata-Version: 2.1
Name: masonite-socketio-driver
Version: 2.1.0
Summary: Socket IO Broadcast Driver for Masonite
Home-page: https://github.com/py-package/masonite-socketio-driver
Author: Yubaraj Shrestha
Author-email: yubaraj@pypackage.com
License: MIT
Project-URL: Bug Tracker, https://github.com/py-package/masonite-socketio-driver/issues
Keywords: masonite,socket-io,broadcast,masonite-socket-io-broadcast-driver
Platform: UNKNOWN
Classifier: Development Status :: 5 - Production/Stable
Classifier: Intended Audience :: Developers
Classifier: Environment :: Web Environment
Classifier: License :: OSI Approved :: MIT License
Classifier: Operating System :: OS Independent
Classifier: Programming Language :: Python :: 3.7
Classifier: Programming Language :: Python :: 3.8
Classifier: Programming Language :: Python :: 3.9
Classifier: Topic :: Software Development :: Libraries :: Application Frameworks
Classifier: Topic :: Software Development :: Libraries :: Python Modules
Classifier: Framework :: Masonite
License-File: LICENSE
Requires-Dist: masonite (>=4.0<5.0)
Requires-Dist: socket.io-emitter
Requires-Dist: redis
Requires-Dist: msgpack
Provides-Extra: dev
Requires-Dist: black ; extra == 'dev'
Requires-Dist: flake8 ; extra == 'dev'
Requires-Dist: coverage ; extra == 'dev'
Requires-Dist: pytest ; extra == 'dev'
Requires-Dist: pytest-cov ; extra == 'dev'
Requires-Dist: twine (>=1.5.0) ; extra == 'dev'
Requires-Dist: wheel ; extra == 'dev'
